clypper/__init__.py
clypper/cli.py
clypper/clypper.py
clypper/video_sources.py
clypper-0.0.3.dist-info/entry_points.txt
clypper-0.0.3.dist-info/LICENSE
clypper-0.0.3.dist-info/WHEEL
clypper-0.0.3.dist-info/METADATA
clypper-0.0.3.dist-info/RECORD
