Metadata-Version: 2.1
Name: clypper
Version: 0.0.3
Summary: Rapidly create supercuts from various video sources.
Home-page: https://github.com/kpj/clypper
License: MIT
Author: kpj
Author-email: kpjkpjkpjkpjkpjkpj@gmail.com
Requires-Python: >=3.6,<4.0
Classifier: License :: OSI Approved :: MIT License
Classifier: Programming Language :: Python :: 3
Classifier: Programming Language :: Python :: 3.6
Classifier: Programming Language :: Python :: 3.7
Classifier: Programming Language :: Python :: 3.8
Requires-Dist: click (>=7.1.2,<8.0.0)
Requires-Dist: moviepy (>=1.0.3,<2.0.0)
Requires-Dist: pytimeparse (>=1.1.8,<2.0.0)
Requires-Dist: pytube3 (>=9.6.4,<10.0.0)
Requires-Dist: sh (>=1.13.1,<2.0.0)
Requires-Dist: tqdm (>=4.46.0,<5.0.0)
Project-URL: Repository, https://github.com/kpj/clypper
